appstoreserverlibrary/__init__.py
appstoreserverlibrary/api_client.py
appstoreserverlibrary/promotional_offer.py
appstoreserverlibrary/receipt_utility.py
appstoreserverlibrary/signed_data_verifier.py
appstoreserverlibrary/models/AccountTenure.py
appstoreserverlibrary/models/AppTransaction.py
appstoreserverlibrary/models/AutoRenewStatus.py
appstoreserverlibrary/models/CheckTestNotificationResponse.py
appstoreserverlibrary/models/ConsumptionRequest.py
appstoreserverlibrary/models/ConsumptionStatus.py
appstoreserverlibrary/models/Data.py
appstoreserverlibrary/models/DeliveryStatus.py
appstoreserverlibrary/models/Environment.py
appstoreserverlibrary/models/ExpirationIntent.py
appstoreserverlibrary/models/ExtendReasonCode.py
appstoreserverlibrary/models/ExtendRenewalDateRequest.py
appstoreserverlibrary/models/ExtendRenewalDateResponse.py
appstoreserverlibrary/models/FirstSendAttemptResult.py
appstoreserverlibrary/models/HistoryResponse.py
appstoreserverlibrary/models/InAppOwnershipType.py
appstoreserverlibrary/models/JWSRenewalInfoDecodedPayload.py
appstoreserverlibrary/models/JWSTransactionDecodedPayload.py
appstoreserverlibrary/models/LastTransactionsItem.py
appstoreserverlibrary/models/LifetimeDollarsPurchased.py
appstoreserverlibrary/models/LifetimeDollarsRefunded.py
appstoreserverlibrary/models/MassExtendRenewalDateRequest.py
appstoreserverlibrary/models/MassExtendRenewalDateResponse.py
appstoreserverlibrary/models/MassExtendRenewalDateStatusResponse.py
appstoreserverlibrary/models/NotificationHistoryRequest.py
appstoreserverlibrary/models/NotificationHistoryResponse.py
appstoreserverlibrary/models/NotificationHistoryResponseItem.py
appstoreserverlibrary/models/NotificationTypeV2.py
appstoreserverlibrary/models/OfferType.py
appstoreserverlibrary/models/OrderLookupResponse.py
appstoreserverlibrary/models/OrderLookupStatus.py
appstoreserverlibrary/models/Platform.py
appstoreserverlibrary/models/PlayTime.py
appstoreserverlibrary/models/PriceIncreaseStatus.py
app_store_server-0.1.0.dist-info/LICENSE.txt
app_store_server-0.1.0.dist-info/METADATA
app_store_server-0.1.0.dist-info/NOTICE.txt
app_store_server-0.1.0.dist-info/WHEEL
app_store_server-0.1.0.dist-info/top_level.txt
app_store_server-0.1.0.dist-info/RECORD
