Metadata-Version: 2.1
Name: app-store-server
Version: 0.1.0
Summary: The App Store Server Library
Requires-Python: >=3.7, <4
License-File: LICENSE.txt
License-File: NOTICE.txt
Requires-Dist: attrs (>=21.3.0)
Requires-Dist: PyJWT (<3,>=2.6.0)
Requires-Dist: requests (<3,>=2.28.0)
Requires-Dist: cryptography (<42,>=40.0.0)
Requires-Dist: pyOpenSSL (<24,>=23.1.1)
Requires-Dist: asn1 (==2.7.0)
Requires-Dist: cattrs (==23.1.2)
